rosettasciio-0.12.0.dist-info/licenses/COPYING.txt
rsciio/__init__.py
rsciio/_docstrings.py
rsciio/_hierarchical.py
rsciio/_logger.py
rsciio/exceptions.py
rsciio/arina/__init__.py
rsciio/arina/_api.py
rsciio/arina/specifications.yaml
rsciio/blockfile/__init__.py
rsciio/blockfile/_api.py
rsciio/blockfile/specifications.yaml
rsciio/bruker/__init__.py
rsciio/bruker/_api.py
rsciio/bruker/_utils.py
rsciio/bruker/specifications.yaml
rsciio/bruker/unbcf_fast.pyx
rsciio/delmic/__init__.py
rsciio/delmic/_api.py
rsciio/delmic/specifications.yaml
rsciio/dens/__init__.py
rsciio/dens/_api.py
rsciio/dens/specifications.yaml
rsciio/digitalmicrograph/__init__.py
rsciio/digitalmicrograph/_api.py
rsciio/digitalmicrograph/specifications.yaml
rsciio/digitalsurf/__init__.py
rsciio/digitalsurf/_api.py
rsciio/digitalsurf/specifications.yaml
rsciio/edax/__init__.py
rsciio/edax/_api.py
rsciio/edax/specifications.yaml
rsciio/emd/__init__.py
rsciio/emd/_api.py
rsciio/emd/_emd_ncem.py
rsciio/emd/_emd_velox.py
rsciio/emd/specifications.yaml
rsciio/empad/__init__.py
rsciio/empad/_api.py
rsciio/empad/specifications.yaml
rsciio/hamamatsu/__init__.py
rsciio/hamamatsu/_api.py
rsciio/hamamatsu/specifications.yaml
rsciio/hspy/__init__.py
rsciio/hspy/_api.py
rsciio/hspy/specifications.yaml
rsciio/image/__init__.py
rsciio/image/_api.py
rsciio/image/specifications.yaml
rsciio/impulse/__init__.py
rsciio/impulse/_api.py
rsciio/impulse/specifications.yaml
rsciio/jeol/__init__.py
rsciio/jeol/_api.py
rsciio/jeol/specifications.yaml
rsciio/jobinyvon/__init__.py
rsciio/jobinyvon/_api.py
rsciio/jobinyvon/specifications.yaml
rsciio/mrc/__init__.py
rsciio/mrc/_api.py
rsciio/mrc/specifications.yaml
rsciio/mrcz/__init__.py
rsciio/mrcz/_api.py
rsciio/mrcz/specifications.yaml
rsciio/msa/__init__.py
rsciio/msa/_api.py
rsciio/msa/specifications.yaml
rsciio/netcdf/__init__.py
rsciio/netcdf/_api.py
rsciio/netcdf/specifications.yaml
rsciio/nexus/__init__.py
rsciio/nexus/_api.py
rsciio/nexus/specifications.yaml
rsciio/numpy/__init__.py
rsciio/numpy/_api.py
rosettasciio-0.12.0.dist-info/METADATA
rosettasciio-0.12.0.dist-info/WHEEL
rosettasciio-0.12.0.dist-info/top_level.txt
rosettasciio-0.12.0.dist-info/RECORD
