Metadata-Version: 2.4
Name: rosettasciio
Version: 0.12.0
Summary: Reading and writing scientific file formats
License-Expression: GPL-3.0-or-later
Project-URL: Homepage, https://hyperspy.org/rosettasciio
Project-URL: Bug Reports, https://github.com/hyperspy/rosettasciio/issues
Project-URL: Source, https://github.com/hyperspy/rosettasciio
Keywords: electron microscopy,hyperspy,input/output,io,microscopy,scientific data formats,spectroscopy,numpy,python,scipy,app5,asw,blo,bcf,de5,dens,dm3,dm4,eds,elid,emd,emi,hdf5,hspy,img,itex,map,mib,mrc,mrcz,msa,nxs,prz,pts,rpl,ser,spc,sur,spx,tvf,tvips,unf,usid,wdf,zspy
Classifier: Development Status :: 4 - Beta
Classifier: Intended Audience :: Developers
Classifier: Intended Audience :: Science/Research
Classifier: Operating System :: OS Independent
Classifier: Programming Language :: Python :: 3.10
Classifier: Programming Language :: Python :: 3.11
Classifier: Programming Language :: Python :: 3.12
Classifier: Programming Language :: Python :: 3.13
Classifier: Programming Language :: Python :: 3.14
Classifier: Programming Language :: Python :: Free Threading :: 1 - Unstable
Classifier: Topic :: Scientific/Engineering
Classifier: Topic :: Scientific/Engineering :: Physics
Classifier: Topic :: Software Development :: Libraries
Requires-Python: >=3.10
License-File: COPYING.txt
Requires-Dist: dask[array]>=2022.9.2
Requires-Dist: python-dateutil
Requires-Dist: numpy>=1.22
Requires-Dist: pint>=0.8
Requires-Dist: python-box!=7.3.1,<8,>=6
Requires-Dist: pyyaml
Provides-Extra: app5
Requires-Dist: h5py>=3.7; extra == "app5"
Provides-Extra: arina
Requires-Dist: h5py>=3.7; extra == "arina"
Requires-Dist: hdf5plugin; extra == "arina"
Provides-Extra: blockfile
Requires-Dist: scikit-image>=0.20; extra == "blockfile"
Provides-Extra: eds-stream
Requires-Dist: sparse; extra == "eds-stream"
Provides-Extra: hdf5
Requires-Dist: h5py>=3.7; extra == "hdf5"
Provides-Extra: image
Requires-Dist: imageio>=2.16; extra == "image"
Requires-Dist: pillow>=9.0.1; extra == "image"
Provides-Extra: mrcz
Requires-Dist: mrcz>=0.3.6; extra == "mrcz"
Provides-Extra: scalebar-export
Requires-Dist: matplotlib-scalebar; extra == "scalebar-export"
Requires-Dist: matplotlib>=3.6; extra == "scalebar-export"
Provides-Extra: speed
Requires-Dist: numba>=0.56; extra == "speed"
Provides-Extra: tiff
Requires-Dist: tifffile>=2022.7.28; extra == "tiff"
Requires-Dist: imagecodecs; extra == "tiff"
Provides-Extra: usid
Requires-Dist: pyUSID>=0.0.11; extra == "usid"
Provides-Extra: zspy
Requires-Dist: zarr<3,>=2; extra == "zspy"
Requires-Dist: msgpack; extra == "zspy"
Provides-Extra: tests
Requires-Dist: filelock; extra == "tests"
Requires-Dist: pooch; extra == "tests"
Requires-Dist: pytest>=3.6; extra == "tests"
Requires-Dist: pytest-xdist; extra == "tests"
Requires-Dist: pytest-rerunfailures; extra == "tests"
Requires-Dist: pytest-cov; extra == "tests"
Requires-Dist: setuptools_scm; extra == "tests"
Provides-Extra: doc
Requires-Dist: numpydoc>=1.6.0; extra == "doc"
Requires-Dist: pooch; extra == "doc"
Requires-Dist: pydata-sphinx-theme>=0.13; extra == "doc"
Requires-Dist: setuptools_scm; extra == "doc"
Requires-Dist: sphinx; extra == "doc"
Requires-Dist: sphinx-favicon; extra == "doc"
Requires-Dist: sphinxcontrib-towncrier>=0.5.0a0; extra == "doc"
Requires-Dist: sphinx-copybutton; extra == "doc"
Requires-Dist: towncrier; extra == "doc"
Requires-Dist: sphinx_design; extra == "doc"
Provides-Extra: all
Requires-Dist: rosettasciio[blockfile]; extra == "all"
Requires-Dist: rosettasciio[eds-stream]; extra == "all"
Requires-Dist: rosettasciio[hdf5]; extra == "all"
Requires-Dist: rosettasciio[app5]; extra == "all"
Requires-Dist: rosettasciio[arina]; extra == "all"
Requires-Dist: rosettasciio[mrcz]; extra == "all"
Requires-Dist: rosettasciio[scalebar_export]; extra == "all"
Requires-Dist: rosettasciio[speed]; extra == "all"
Requires-Dist: rosettasciio[tiff]; extra == "all"
Requires-Dist: rosettasciio[usid]; extra == "all"
Requires-Dist: rosettasciio[zspy]; extra == "all"
Provides-Extra: dev
Requires-Dist: ruff; extra == "dev"
Requires-Dist: rosettasciio[doc]; extra == "dev"
Requires-Dist: rosettasciio[all]; extra == "dev"
Requires-Dist: rosettasciio[tests]; extra == "dev"
Dynamic: license-file
